structure_clustering/__init__.py
structure_clustering/__main__.py
structure_clustering/_core.cp312-win_amd64.pyd
structure_clustering/import_multi_xyz.py
structure_clustering-1.1.2.dist-info/METADATA
structure_clustering-1.1.2.dist-info/WHEEL
structure_clustering-1.1.2.dist-info/entry_points.txt
structure_clustering-1.1.2.dist-info/licenses/LICENSE
structure_clustering-1.1.2.dist-info/RECORD
