Metadata-Version: 2.1
Name: structure_clustering
Version: 1.1.2
Summary:  Python package to cluster molecular structures into groups of similar ones.
Author: Gabriel Schöpfer, Milan Ončák
Author-Email: Michael Gatt <Michael.Gatt@student.uibk.ac.at>
Maintainer-Email: Michael Gatt <Michael.Gatt@student.uibk.ac.at>
License: MIT License
Classifier: Development Status :: 5 - Production/Stable
Classifier: License :: OSI Approved :: MIT License
Classifier: Programming Language :: Python :: 3 :: Only
Classifier: Programming Language :: Python :: 3.7
Classifier: Programming Language :: Python :: 3.8
Classifier: Programming Language :: Python :: 3.9
Classifier: Programming Language :: Python :: 3.10
Classifier: Programming Language :: Python :: 3.11
Classifier: Programming Language :: Python :: 3.12
Classifier: Intended Audience :: Science/Research
Classifier: Topic :: Scientific/Engineering :: Chemistry
Classifier: Topic :: Scientific/Engineering :: Physics
Project-URL: Documentation, https://github.com/photophys/structure_clustering/blob/main/README.md
Project-URL: Repository, https://github.com/photophys/structure_clustering
Project-URL: Issues, https://github.com/photophys/structure_clustering/issues
Requires-Python: >=3.7
Requires-Dist: argparse
Requires-Dist: toml
Requires-Dist: numpy
